{"cameraMode":{"drawMode":0,"name":"Shaded","section":"Shading Mode"},"sceneLighting":false,"audioPlay":false,"sceneViewState":{"showFog":true,"showMaterialUpdate":false,"showSkybox":false,"showFlares":true,"showImageEffects":true,"showParticleSystems":true},"in2DMode":false,"pivot":{"x":0.008900731801986695,"y":1.157541036605835,"z":0.32440125942230227},"rotation":{"x":0.07493685930967331,"y":0.06686495244503021,"z":-0.004540778696537018,"w":0.9951745271682739},"size":0.736173152923584,"orthographic":false}